AUTHORS.txt
LICENSE.txt
README.rst
requirements.txt
setup.py
nidhogg/__init__.py
nidhogg/clustermode.py
nidhogg/compatible.py
nidhogg/core.py
nidhogg/http.py
nidhogg/sevenmode.py
nidhogg/utils.py
nidhogg.egg-info/PKG-INFO
nidhogg.egg-info/SOURCES.txt
nidhogg.egg-info/dependency_links.txt
nidhogg.egg-info/requires.txt
nidhogg.egg-info/top_level.txt