Metadata-Version: 1.1
Name: nidhogg
Version: 3.6.1
Summary: wrapper interface to Netapp filers
Home-page: https://github.com/ifxit/nidhogg
Author: Christian Assing, Roland Wohlfahrt
Author-email: christian.assing@infineon.com, roland.wohlfahrt@infineon.com
License: MIT License, Copyright (c) 2017 Infineon Technologies AG
Keywords: netapp,vserver,sevenmode,ontapi
Platform: a
Platform: n
Platform: y
Classifier: Development Status :: 5 - Production/Stable
Classifier: Intended Audience :: Developers
Classifier: License :: OSI Approved :: MIT License
Classifier: Operating System :: OS Independent
Classifier: Programming Language :: Python :: 2
Classifier: Programming Language :: Python :: 2.7
Classifier: Programming Language :: Python :: 3
Classifier: Programming Language :: Python :: 3.4
Classifier: Programming Language :: Python :: 3.5
Classifier: Programming Language :: Python :: 3.6
Classifier: Natural Language :: English
Classifier: Topic :: Internet :: WWW/HTTP
Classifier: Topic :: Software Development :: Libraries :: Python Modules
Classifier: Topic :: System :: Archiving
Classifier: Topic :: System :: Systems Administration
